logit/__init__.py
logit/linear_model.py
logits-2025.0.0.dist-info/METADATA
logits-2025.0.0.dist-info/WHEEL
logits-2025.0.0.dist-info/top_level.txt
logits-2025.0.0.dist-info/RECORD
